{"cameraMode":{"drawMode":0,"name":"Shaded","section":"Shading Mode"},"sceneLighting":false,"audioPlay":false,"sceneViewState":{"m_AlwaysRefresh":false,"showFog":true,"showSkybox":false,"showFlares":true,"showImageEffects":true,"showParticleSystems":true,"showVisualEffectGraphs":true,"m_FxEnabled":true},"in2DMode":false,"pivot":{"x":0.0,"y":0.029999997466802598,"z":0.0},"rotation":{"x":-0.3690122961997986,"y":-0.039858296513557437,"z":0.01583907939493656,"w":-0.9284418225288391},"size":35.35537338256836,"orthographic":false}